scribble_from_segmentation/__init__.py
scribble_from_segmentation/scribble_from_segmentation.py
scribble_from_segmentation-0.0.3.dist-info/METADATA
scribble_from_segmentation-0.0.3.dist-info/WHEEL
scribble_from_segmentation-0.0.3.dist-info/entry_points.txt
scribble_from_segmentation-0.0.3.dist-info/RECORD
