Metadata-Version: 2.4
Name: scribble-from-segmentation
Version: 0.0.3
Summary: Generate scribble annotations from segmentation masks
Author: Alex Senden
Maintainer: Alex Senden
License: MIT
Keywords: computer-vision,image-annotation,image-processing,machine-learning,segmentation
Classifier: Development Status :: 3 - Alpha
Classifier: Intended Audience :: Developers
Classifier: License :: OSI Approved :: MIT License
Classifier: Programming Language :: Python :: 3
Classifier: Programming Language :: Python :: 3.8
Classifier: Programming Language :: Python :: 3.9
Classifier: Programming Language :: Python :: 3.10
Classifier: Programming Language :: Python :: 3.11
Classifier: Topic :: Scientific/Engineering :: Image Processing
Requires-Python: >=3.8
Requires-Dist: numpy
Requires-Dist: opencv-python
Requires-Dist: pillow
Requires-Dist: scikit-image
